defigraph/Edge.py
defigraph/Graph.py
defigraph/Pool.py
defigraph/Vertex.py
defigraph/__init__.py
defigraph-0.1.2.dist-info/LICENSE
defigraph-0.1.2.dist-info/METADATA
defigraph-0.1.2.dist-info/WHEEL
defigraph-0.1.2.dist-info/top_level.txt
defigraph-0.1.2.dist-info/RECORD
