Metadata-Version: 2.2
Name: defigraph
Version: 0.1.2
Summary: A package for creating a directed graphs based on DeFi protocols
Author-email: Meek Msaki <meek.dev3@gmail.com>
Project-URL: Homepage, https://github.com/mmsaki/defigraph
Project-URL: Issues, https://github.com/mmsaki/defigraph/issues
Classifier: Programming Language :: Python :: 3
Classifier: License :: OSI Approved :: MIT License
Classifier: Operating System :: OS Independent
Requires-Python: >=3.10
License-File: LICENSE
Requires-Dist: ipykernel>=6.29.5
Requires-Dist: load-dotenv>=0.1.0
Requires-Dist: matplotlib>=3.7.5
Requires-Dist: networkx>=3.4
Requires-Dist: pytest>=8.3.3
Requires-Dist: ruff>=0.7.4
Requires-Dist: web3>=7.5.0
Provides-Extra: dev
Requires-Dist: bumpver; extra == "dev"
Requires-Dist: pytest; extra == "dev"
